corvo/__init__.py
corvo/main.py
corvo/Corvo.egg-info/PKG-INFO
corvo/Corvo.egg-info/SOURCES.txt
corvo/Corvo.egg-info/dependency_links.txt
corvo/Corvo.egg-info/entry_points.txt
corvo/Corvo.egg-info/requires.txt
corvo/Corvo.egg-info/top_level.txt
corvo/corvo.egg-info/PKG-INFO
corvo/corvo.egg-info/SOURCES.txt
corvo/corvo.egg-info/dependency_links.txt
corvo/corvo.egg-info/entry_points.txt
corvo/corvo.egg-info/requires.txt
corvo/corvo.egg-info/top_level.txt
corvo/lib/intelxapi.py
corvo/lib/leakParser.py
corvo/lib/__pycache__/intelxapi.cpython-312.pyc
corvo/lib/__pycache__/leakParser.cpython-312.pyc
corvo/media/corvo_workflow.png
corvo-0.4.dist-info/METADATA
corvo-0.4.dist-info/WHEEL
corvo-0.4.dist-info/entry_points.txt
corvo-0.4.dist-info/top_level.txt
corvo-0.4.dist-info/RECORD
