Metadata-Version: 2.1
Name: corvo
Version: 0.4
Summary: A credential harvester, powered by the IntelX API.
Home-page: https://github.com/santiag02/Corvo
Author: Camila Santiago
Keywords: leaks,credentials,intelx,data-leak,infostealer
Requires-Dist: python-dateutil
Requires-Dist: requests
